[
{"country" : "Abkhazia", "code" : "+99544"},
{"country" : "Afghanistan", "code" : "+93"},
{"country" : "Åland Islands", "code" : "+35818"},
{"country" : "Albania", "code" : "+355"},
{"country" : "Algeria", "code" : "+213"},
{"country" : "American Samoa", "code" : "+1684"},
{"country" : "Andorra", "code" : "+376"},
{"country" : "Angola", "code" : "+244"},
{"country" : "Anguilla", "code" : "+1264"},
{"country" : "AntiguaandBarbuda", "code" : "+1268"},
{"country" : "Argentina", "code" : "+54"},
{"country" : "Armenia", "code" : "+374"},
{"country" : "Aruba", "code" : "+297"},
{"country" : "Ascension", "code" : "+247"},
{"country" : "Australia", "code" : "+61"},
{"country" : "Australian External Territories", "code" : "+672"},
{"country" : "Austria", "code" : "+43"},
{"country" : "Azerbaijan", "code" : "+994"},
{"country" : "Bahamas", "code" : "+1242"},
{"country" : "Bahrain", "code" : "+973"},
{"country" : "Bangladesh", "code" : "+880"},
{"country" : "Barbados", "code" : "+1246"},
{"country" : "Barbuda", "code" : "+1268"},
{"country" : "Belarus", "code" : "+375"},
{"country" : "Belgium", "code" : "+32"},
{"country" : "Belize", "code" : "+501"},
{"country" : "Benin", "code" : "+229"},
{"country" : "Bermuda", "code" : "+1441"},
{"country" : "Bhutan", "code" : "+975"},
{"country" : "Bolivia", "code" : "+591"},
{"country" : "Bonaire", "code" : "+5997"},
{"country" : "Bosniaand Herzegovina", "code" : "+387"},
{"country" : "Botswana", "code" : "+267"},
{"country" : "Brazil", "code" : "+55"},
{"country" : "British Indian Ocean Territory", "code" : "+246"},
{"country" : "British Virgin Islands", "code" : "+1284"},
{"country" : "Brunei Darussalam", "code" : "+673"},
{"country" : "Bulgaria", "code" : "+359"},
{"country" : "Burkina Faso", "code" : "+226"},
{"country" : "Burundi", "code" : "+257"},
{"country" : "Cambodia", "code" : "+855"},
{"country" : "Cameroon", "code" : "+237"},
{"country" : "Canada", "code" : "+1"},
{"country" : "CapeVerde", "code" : "+238"},
{"country" : "Caribbean Netherlands", "code" : "+5997"},
{"country" : "Cayman Islands", "code" : "+1345"},
{"country" : "Central African Republic", "code" : "+236"},
{"country" : "Chad", "code" : "+235"},
{"country" : "Chatham Island, NewZealand", "code" : "+64"},
{"country" : "Chile", "code" : "+56"},
{"country" : "China", "code" : "+86"},
{"country" : "Christmas Island", "code" : "+61"},
{"country" : "Cocos (Keeling) Islands", "code" : "+61"},
{"country" : "Colombia", "code" : "+57"},
{"country" : "Comoros", "code" : "+269"},
{"country" : "Congo", "code" : "+242"},
{"country" : "Congo, Democratic Republic of the (Zaire)", "code" : "+243"},
{"country" : "Cook Islands", "code" : "+682"},
{"country" : "Costa Rica", "code" : "+506"},
{"country" : "Côte d'Ivoire", "code" : "+225"},
{"country" : "Croatia", "code" : "+385"},
{"country" : "Cuba", "code" : "+53"},
{"country" : "Guantanamo Bay, Cuba", "code" : "+5399"},
{"country" : "Curaçao", "code" : "+5999"},
{"country" : "Cyprus", "code" : "+357"},
{"country" : "Czech Republic", "code" : "+420"},
{"country" : "Denmark", "code" : "+45"},
{"country" : "Diego Garcia", "code" : "+246"},
{"country" : "Djibouti", "code" : "+253"},
{"country" : "Dominica", "code" : "+1767"},
{"country" : "Dominican Republic", "code" : "+1849"},
{"country" : "East Timor", "code" : "+670"},
{"country" : "Easter Island", "code" : "+56"},
{"country" : "Ecuador", "code" : "+593"},
{"country" : "Egypt", "code" : "+20"},
{"country" : "El Salvador", "code" : "+503"},
{"country" : "Ellipso (Mobile Satellite service)", "code" : "+8813"},
{"country" : "EMSAT (Mobile Satellite service)", "code" : "+88213"},
{"country" : "Equatorial Guinea", "code" : "+240"},
{"country" : "Eritrea", "code" : "+291"},
{"country" : "Estonia", "code" : "+372"},
{"country" : "Ethiopia", "code" : "+251"},
{"country" : "Falkland Islands", "code" : "+500"},
{"country" : "Faroe Islands", "code" : "+298"},
{"country" : "Fiji", "code" : "+679"},
{"country" : "Finland", "code" : "+358"},
{"country" : "France", "code" : "+33"},
{"country" : "French Antilles", "code" : "+596"},
{"country" : "French Guiana", "code" : "+594"},
{"country" : "French Polynesia", "code" : "+689"},
{"country" : "Gabon", "code" : "+241"},
{"country" : "Gambia", "code" : "+220"},
{"country" : "Georgia", "code" : "+995"},
{"country" : "Germany", "code" : "+49"},
{"country" : "Ghana", "code" : "+233"},
{"country" : "Gibraltar", "code" : "+350"},
{"country" : "Global Mobile Satellite System (GMSS)", "code" : "+881"},
{"country" : "Globalstar (Mobile Satellite Service)", "code" : "+8818"},
{"country" : "Greece", "code" : "+30"},
{"country" : "Greenland", "code" : "+299"},
{"country" : "Grenada", "code" : "+1473"},
{"country" : "Guadeloupe", "code" : "+590"},
{"country" : "Guam", "code" : "+1671"},
{"country" : "Guatemala", "code" : "+502"},
{"country" : "Guernsey", "code" : "+44"},
{"country" : "Guinea", "code" : "+224"},
{"country" : "Guinea-Bissau", "code" : "+245"},
{"country" : "Guyana", "code" : "+592"},
{"country" : "Haiti", "code" : "+509"},
{"country" : "Honduras", "code" : "+504"},
{"country" : "Hong Kong", "code" : "+852"},
{"country" : "Hungary", "code" : "+36"},
{"country" : "Iceland", "code" : "+354"},
{"country" : "ICO Global (Mobile Satellite Service)", "code" : "+8810"},
{"country" : "India", "code" : "+91"},
{"country" : "Indonesia", "code" : "+62"},
{"country" : "Inmarsat SNAC", "code" : "+870"},
{"country" : "International Freephone Service", "code" : "+800"},
{"country" : "International Shared Cost Service (ISCS)", "code" : "+808"},
{"country" : "Iran", "code" : "+98"},
{"country" : "Iraq", "code" : "+964"},
{"country" : "Ireland", "code" : "+353"},
{"country" : "Iridium (Mobile Satellite service)", "code" : "+8817"},
{"country" : "IsleofMan", "code" : "+44"},
{"country" : "Israel", "code" : "+972"},
{"country" : "Italy", "code" : "+39"},
{"country" : "Jamaica", "code" : "+1876"},
{"country" : "Jan Mayen", "code" : "+4779"},
{"country" : "Japan", "code" : "+81"},
{"country" : "Jersey", "code" : "+44"},
{"country" : "Jordan", "code" : "+962"},
{"country" : "Kazakhstan", "code" : "+77[notes1]"},
{"country" : "Kenya", "code" : "+254"},
{"country" : "Kiribati", "code" : "+686"},
{"country" : "Korea, North", "code" : "+850"},
{"country" : "Korea, South", "code" : "+82"},
{"country" : "Kosovo", "code" : "+383"},
{"country" : "Kuwait", "code" : "+965"},
{"country" : "Kyrgyzstan", "code" : "+996"},
{"country" : "Laos", "code" : "+856"},
{"country" : "Latvia", "code" : "+371"},
{"country" : "Lebanon", "code" : "+961"},
{"country" : "Lesotho", "code" : "+266"},
{"country" : "Liberia", "code" : "+231"},
{"country" : "Libya", "code" : "+218"},
{"country" : "Liechtenstein", "code" : "+423"},
{"country" : "Lithuania", "code" : "+370"},
{"country" : "Luxembourg", "code" : "+352"},
{"country" : "Macau", "code" : "+853"},
{"country" : "Macedonia", "code" : "+389"},
{"country" : "Madagascar", "code" : "+261"},
{"country" : "Malawi", "code" : "+265"},
{"country" : "Malaysia", "code" : "+60"},
{"country" : "Maldives", "code" : "+960"},
{"country" : "Mali", "code" : "+223"},
{"country" : "Malta", "code" : "+356"},
{"country" : "Marshall Islands", "code" : "+692"},
{"country" : "Martinique", "code" : "+596"},
{"country" : "Mauritania", "code" : "+222"},
{"country" : "Mauritius", "code" : "+230"},
{"country" : "Mayotte", "code" : "+262"},
{"country" : "Mexico", "code" : "+52"},
{"country" : "Micronesia, Federated States of", "code" : "+691"},
{"country" : "Midway Island, USA", "code" : "+1808"},
{"country" : "Moldova", "code" : "+373"},
{"country" : "Monaco", "code" : "+377"},
{"country" : "Mongolia", "code" : "+976"},
{"country" : "Montenegro", "code" : "+382"},
{"country" : "Montserrat", "code" : "+1664"},
{"country" : "Morocco", "code" : "+212"},
{"country" : "Mozambique", "code" : "+258"},
{"country" : "Myanmar", "code" : "+95"},
{"country" : "Namibia", "code" : "+264"},
{"country" : "Nauru", "code" : "+674"},
{"country" : "Nepal", "code" : "+977"},
{"country" : "Netherlands", "code" : "+31"},
{"country" : "Nevis", "code" : "+1869"},
{"country" : "New Caledonia", "code" : "+687"},
{"country" : "New Zealand", "code" : "+64"},
{"country" : "Nicaragua", "code" : "+505"},
{"country" : "Niger", "code" : "+227"},
{"country" : "Nigeria", "code" : "+234"},
{"country" : "Niue", "code" : "+683"},
{"country" : "Norfolk Island", "code" : "+672"},
{"country" : "Northern Cyprus", "code" : "+90392"},
{"country" : "Northern Mariana Islands", "code" : "+1670"},
{"country" : "Norway", "code" : "+47"},
{"country" : "Oman", "code" : "+968"},
{"country" : "Pakistan", "code" : "+92"},
{"country" : "Palau", "code" : "+680"},
{"country" : "Palestine, State of", "code" : "+970"},
{"country" : "Panama", "code" : "+507"},
{"country" : "Papua New Guinea", "code" : "+675"},
{"country" : "Paraguay", "code" : "+595"},
{"country" : "Peru", "code" : "+51"},
{"country" : "Philippines", "code" : "+63"},
{"country" : "Pitcairn Islands", "code" : "+64"},
{"country" : "Poland", "code" : "+48"},
{"country" : "Portugal", "code" : "+351"},
{"country" : "Puerto Rico", "code" : "+1787,", "code" : "+1939"},
{"country" : "Qatar", "code" : "+974"},
{"country" : "Réunion", "code" : "+262"},
{"country" : "Romania", "code" : "+40"},
{"country" : "Russia", "code" : "+7"},
{"country" : "Rwanda", "code" : "+250"},
{"country" : "Saba", "code" : "+5994"},
{"country" : "Saint Barthélemy", "code" : "+590"},
{"country" : "Saint Helena", "code" : "+290"},
{"country" : "Saint Kitts and Nevis", "code" : "+1869"},
{"country" : "Saint Lucia", "code" : "+1758"},
{"country" : "Saint Martin (France)", "code" : "+590"},
{"country" : "Saint Pierre and Miquelon", "code" : "+508"},
{"country" : "Saint Vincent and the Grenadines", "code" : "+1784"},
{"country" : "Samoa", "code" : "+685"},
{"country" : "San Marino", "code" : "+378"},
{"country" : "São Tomé and Príncipe", "code" : "+239"},
{"country" : "Saudi Arabia", "code" : "+966"},
{"country" : "Senegal", "code" : "+221"},
{"country" : "Serbia", "code" : "+381"},
{"country" : "Seychelles", "code" : "+248"},
{"country" : "Sierra Leone", "code" : "+232"},
{"country" : "Singapore", "code" : "+65"},
{"country" : "Sint Eustatius", "code" : "+5993"},
{"country" : "Sint Maarten (Netherlands)", "code" : "+1721"},
{"country" : "Slovakia", "code" : "+421"},
{"country" : "Slovenia", "code" : "+386"},
{"country" : "Solomon Islands", "code" : "+677"},
{"country" : "Somalia", "code" : "+252"},
{"country" : "South Africa", "code" : "+27"},
{"country" : "South Georgia and the South Sandwich Islands", "code" : "+500"},
{"country" : "South Ossetia", "code" : "+99534"},
{"country" : "South Sudan", "code" : "+211"},
{"country" : "Spain", "code" : "+34"},
{"country" : "Sri Lanka", "code" : "+94"},
{"country" : "Sudan", "code" : "+249"},
{"country" : "Suriname", "code" : "+597"},
{"country" : "Svalbard", "code" : "+4779"},
{"country" : "Swaziland", "code" : "+268"},
{"country" : "Sweden", "code" : "+46"},
{"country" : "Switzerland", "code" : "+41"},
{"country" : "Syria", "code" : "+963"},
{"country" : "Taiwan", "code" : "+886"},
{"country" : "Tajikistan", "code" : "+992"},
{"country" : "Tanzania", "code" : "+255"},
{"country" : "Thailand", "code" : "+66"},
{"country" : "Thuraya (Mobile Satellite service)", "code" : "+88216"},
{"country" : "Togo", "code" : "+228"},
{"country" : "Tokelau", "code" : "+690"},
{"country" : "Tonga", "code" : "+676"},
{"country" : "Trinidad and Tobago", "code" : "+1868"},
{"country" : "Tristanda Cunha", "code" : "+2908"},
{"country" : "Tunisia", "code" : "+216"},
{"country" : "Turkey", "code" : "+90"},
{"country" : "Turkmenistan", "code" : "+993"},
{"country" : "Turks and Caicos Islands", "code" : "+1649"},
{"country" : "Tuvalu", "code" : "+688"},
{"country" : "Uganda", "code" : "+256"},
{"country" : "Ukraine", "code" : "+380"},
{"country" : "United Arab Emirates", "code" : "+971"},
{"country" : "United Kingdom", "code" : "+44"},
{"country" : "United States", "code" : "+1"},
{"country" : "Universal Personal Telecommunications (UPT)", "code" : "+878"},
{"country" : "Uruguay", "code" : "+598"},
{"country" : "US Virgin Islands", "code" : "+1340"},
{"country" : "Uzbekistan", "code" : "+998"},
{"country" : "Vanuatu", "code" : "+678"},
{"country" : "Venezuela", "code" : "+58"},
{"country" : "Vatican City State (Holy See)", "code" : "+379"},
{"country" : "Vietnam", "code" : "+84"},
{"country" : "Wake Island,USA", "code" : "+1808"},
{"country" : "Wallis and Futuna", "code" : "+681"},
{"country" : "Yemen", "code" : "+967"},
{"country" : "Zambia", "code" : "+260"},
{"country" : "Zanzibar", "code" : "+255"},
{"country" : "Zimbabwe", "code" : "+263"}
]
